{"data":{"site":{"siteMetadata":{"title":"Firefox Concepts","description":"A simple splash site generator for evaluating product concepts","repo":"https://github.com/johngruen"}},"markdownRemark":{"frontmatter":{"title":"Good Browser"}},"allMarkdownRemark":{"edges":[{"node":{"frontmatter":{"title":"Version Two","description":"Broadcast Your Cause","date":"2010-10-15"},"fields":{"slug":"/good-browser/v2/"}}},{"node":{"frontmatter":{"title":"Version One","description":"Make Meaningful Connections","date":"2010-10-15"},"fields":{"slug":"/good-browser/v1/"}}}]}},"pageContext":{"slug":"/good-browser/","type":"ProductGroup"}}